aws_assume_role/__init__.py
aws_assume_role/__main__.py
aws_assume_role/assumer.py
aws_assume_role/cli.py
aws_assume_role/options.py
aws_assume_role/utils.py
aws_assume_role-1.1.0.dist-info/LICENSE
aws_assume_role-1.1.0.dist-info/METADATA
aws_assume_role-1.1.0.dist-info/WHEEL
aws_assume_role-1.1.0.dist-info/entry_points.txt
aws_assume_role-1.1.0.dist-info/top_level.txt
aws_assume_role-1.1.0.dist-info/RECORD
